{
    "record1": {
        "<1>": "",
        "<2>": "\t\t\t\t\tSYSTEM RESOURCE FILE",
        "<3>": "\t",
        "<4>": "This file is used by ResToString and with UIRES_EQUATES, REPRES_EQUATES, and WINRES_EQUATES",
        "<5>": "",
        "<6>": "WIN100 :PS is not running",
        "<7>": "WIN101 :Window already exists",
        "<8>": "WIN102 : compilation failed!",
        "<9>": "",
        "<10>": "WIN110 : - <New Entry>",
        "<11>": "WIN111 : - <QBF: Define Query>",
        "<12>": "WIN112 : - <QBF: Query In Progress>",
        "<13>": "WIN113 : - <QBF Browse: ",
        "<14>": "WIN114 : - <Entry Locked, View Only>",
        "<15>": "",
        "<16>": "",
        "<17>": "WIN120 :QBF Query Criteria",
        "<18>": "WIN130 :Application Note",
        "<19>": "WIN131 :Lotus Notes reported an error not known by OpenInsight",
        "<20>": "WIN132 :Application Manager",
        "<21>": "WIN133 :Invalid item type '%1%'",
        "<22>": "WIN134 :Cannot start form %1%",
        "<23>": "WIN135 :Help is not available.",
        "<24>": "WIN136 :Options are not available.",
        "<25>": "",
        "<26>": "REP100 :Select Repository",
        "<27>": "REP101 :Select Mirror",
        "<28>": "REP102 :Compare Rows",
        "<29>": "REP103 :Repository / Mirror Comparison ",
        "<30>": "REP104 :Selecting table...",
        "<31>": "REP105 :Comparing tables...",
        "<32>": "REP106 :A physical error has occurred in the %1% table.",
        "<33>": "REP107 :A fatal error has occurred in the %1% table.",
        "<34>": "REP108 :Row %1% shows differences.",
        "<35>": "REP109 :Please notify a system administrator.",
        "<36>": "REP110 :Error detail has been written to the OS file 'REVIMAGE.LOG'.",
        "<37>": "REP111 :Error: Attaching the repository mirror file failed.  Mirroring will not be active for this session.",
        "<38>": "REP112 :Aux Value for %1% should be %2% but is '%3%'",
        "<39>": "REP113 :Value: %1% is missing from index %2% Page %3%",
        "<40>": "REP114 :Primary page of %1%  index is missing.",
        "<41>": "REP115 :Page %1% of index %2% is missing.",
        "<42>": "REP116 :Analyzing",
        "<43>": "REP117 :Removing",
        "<44>": "REP118 :Adding",
        "<45>": "REP119 :Indexing",
        "<46>": "REP120 :Removing from Index",
        "<47>": "REP121 :Database/Repository Synchronization",
        "<48>": "REP122 :Getting Database Table List",
        "<49>": "REP123 :Getting Repository Table List",
        "<50>": "REP124 :Getting Remove List",
        "<51>": "REP125 :Remove: %1%",
        "<52>": "REP126 :Get Add List",
        "<53>": "REP127 :Add: %1%",
        "<54>": "REP128 :Source",
        "<55>": "REP129 :Debug Tables",
        "<56>": "REP130 :Executables",
        "<57>": "REP131 :Inserts",
        "<58>": "REP132 :Stored Procedure/Repository Synchronization",
        "<59>": "REP133 :Getting Stored Procedure Lists",
        "<60>": "REP134 :Removing Entities",
        "<61>": "REP135 :Removing Executable Entities",
        "<62>": "REP136 :Adding Entities",
        "<63>": "REP137 :Adding Executable Entities",
        "<64>": "REP138 :Adding Source Entities",
        "<65>": "REP139 :Adding Insert Entities",
        "<66>": "REP140 :Adding to Index",
        "<67>": "REP141 :Initializing",
        "<68>": "REP142 :Installing",
        "<69>": "REP143 :Selecting records",
        "<70>": "REP144 :Installing records",
        "<71>": "REP145 :The \"%1%\" location contains indexed tables and cannot be altered.",
        "<72>": "REP150 :Undeclared variable",
        "<73>": "REP151 :Unused variable",
        "<74>": "REP152 :Suspected mistyped syscom vars",
        "<75>": "REP153 :Suspected mistyped equate",
        "<76>": "REP154 :Suspected dict.equate orphon",
        "<77>": "REP155 :Line count: %1%",
        "<78>": "REP156 :Extracting",
        "<79>": "REP157 :Building",
        "<80>": "REP158 :Rebuild Repository Indexes",
        "<81>": "REP159 :Extracting Index Information",
        "<82>": "REP160 :Building Index %1% of %2%",
        "<83>": "",
        "<84>": "UI100 :Warning:  The specified column could not be verified",
        "<85>": "UI101 :Field %1% has not been selected",
        "<86>": "UI102 :Column %1% has not been selected",
        "<87>": "UI103 :Column %1% does not exist in the %2% DataSet",
        "<88>": "UI104 :The Column ID value must be numeric",
        "<89>": "UI105 :Invalid Return Type",
        "<90>": "UI106 :New",
        "<91>": "UI107 :Open",
        "<92>": "UI108 :Save As",
        "<93>": "UI109 :Open %1%",
        "<94>": "UI110 :&%1% Name:",
        "<95>": "UI111 :Invalid Column name.%1%Valid column name must be %2%letter[ digit | letter | _ ]...",
        "<96>": "UI112 :Validation Error",
        "<97>": "UI113 :Invalid Data Type.",
        "<98>": "UI114 :Scale for %1% must be between %2% and %3%",
        "<99>": "UI115 :Precision for %1% must be between %2% and %3%",
        "<100>": "UI116 :Do you want to clear current DataSet definition?",
        "<101>": "UI117 :Double click or use Alt-Down for options.",
        "<102>": "UI118 :Native Type",
        "<103>": "UI119 :OpenInsight Type",
        "<104>": "UI120 :Error occurred getting table list",
        "<105>": "UI121 :Modifications cannot be made within a transaction.  You will not be able to save.",
        "<106>": "UI122 :%1% Rows processed",
        "<107>": "UI123 :No options available for %1%",
        "<108>": "UI124 :Column Name,Data Type,Precision,Scale,Nullable,OI Type",
        "<109>": "UI125 :%1% Objects Processed; to view an object's columns, select the object's row and choose \"Query-List Columns\"",
        "<110>": "UI126 :Configuration Error",
        "<111>": "UI127 :The %1% Data Source \"%2%\" has not been configured",
        "<112>": "UI128 :Unable to connect to %1%",
        "<113>": "UI129 :Unable to save the defaults",
        "<114>": "UI130 :The application settings were successfully updated. %1%Do you want to apply these changes to the current session?",
        "<115>": "UI131 :Update Session Settings",
        "<116>": "UI132 :An error occurred reading the defaults",
        "<117>": "UI133 :Error",
        "<118>": "UI140 :&Yes",
        "<119>": "UI141 :&No",
        "<120>": "UI142 :&Cancel",
        "<121>": "UI143 :&OK",
        "<122>": "UI144 :OpenInsight",
        "<123>": "UI145 :Out of memory, or could not create %1% Dialog Box",
        "<124>": "UI146 :The input \"%1%\" does not pass the validation criteria \"%2%\"",
        "<125>": "UI147 :Input Validation Error!",
        "<126>": "UI148 :Bad Parameters! Text field cannot have field marks",
        "<127>": "UI149 :Notes databases and forms",
        "<128>": "UI150 :Notes databases and views",
        "<129>": "UI151 :Registered databases and views",
        "<130>": "UI152 :Registered databases and forms",
        "<131>": "UI153 :Default",
        "<132>": "UI154 :The sequential counter %1% is empty. Enter an initial value.",
        "<133>": "UI155 :Only 1 item exists in the browse list.",
        "<134>": "UI156 :Select item to view ( 1 - %1% )",
        "<135>": "UI157 :Are you sure you wish to delete all notes in the browse list?",
        "<136>": "UI158 :Are you sure you wish to delete the displayed note?",
        "<137>": "UI159 :There are no notes in the browse list.",
        "<138>": "UI160 :QBF Item Select",
        "<139>": "UI161 :QBF Query Criteria",
        "<140>": "UI162 :QBF Query Warning",
        "<141>": "UI163 :Browse list has reached maximum length with %1% entries. Use truncated list?",
        "<142>": "UI164 :Record you are trying to access is already locked, but because of an internal SQl error the current process cannot be canceled.  Please, contact DBA to resolve a problem.",
        "<143>": "UI165 :SQL read message",
        "<144>": "UI166 :Data is required in the following fields %1%",
        "<145>": "UI170 :&Popup Name",
        "<146>": "UI171 :An error ocurred reading the Popup",
        "<147>": "UI172 :An error ocurred writing the Popup",
        "<148>": "UI173 :The Popup has been modified.  Do you want to save the changes?",
        "<149>": "UI174 :Changes will not be permitted",
        "<150>": "UI175 :(Untitled)",
        "<151>": "UI176 :Return Values: %1%",
        "<152>": "UI177 :No Value Returned",
        "<153>": "UI178 :Specify Arguments",
        "<154>": "UI179 :Argument",
        "<155>": {
            "<155,1>": {
                "<155,1,1>": {
                    "<155,1,1,1>": "UI180 :The Popup displays selected fields from Lotus Notes Documents.",
                    "<155,1,1,2>": "",
                    "<155,1,1,3>": "On the following page, select a Notes database, specify either Notes Forms or Views, then select the Fields or Columns to display in the Popup.",
                    "<155,1,1,4>": "",
                    "<155,1,1,5>": "Enter the 'Selection Formula' as a Notes Formula.  To use a View, enter 'Use ' plus the name of the view.\""
                }
            }
        },
        "<156>": {
            "<156,1>": {
                "<156,1,1>": {
                    "<156,1,1,1>": "UI181 :The Popup displays selected columns from a DataSet.",
                    "<156,1,1,2>": "",
                    "<156,1,1,3>": "On the following page, select a DataSet to use as the datasource then select the columns from the DataSet to display in the Popup."
                }
            }
        },
        "<157>": "UI182 :The Popup displays specified columns from a table using a list of keys.",
        "<158>": "UI183 :The Popup displays specified columns from a table using an active cursor",
        "<159>": {
            "<159,1>": {
                "<159,1,1>": {
                    "<159,1,1,1>": "UI184 :The Popup displays data stored in the Popup definition or passed to the Popup programmatically",
                    "<159,1,1,2>": "",
                    "<159,1,1,3>": "Specify the data to display in the 'Literal Data' box on the following page.  Each line in the box corresponds to a Popup row; multiple columns must be separated by the vertical bar character \"|\"."
                }
            }
        },
        "<160>": {
            "<160,1>": {
                "<160,1,1>": {
                    "<160,1,1,1>": "UI185 :The Popup displays multi-valued column data from a specified table row.",
                    "<160,1,1,2>": "",
                    "<160,1,1,3>": "On the following page, specify the table name and the row ID to use.  In the column layout, the 'Column ID' specifies the field position in the row."
                }
            }
        },
        "<161>": {
            "<161,1>": {
                "<161,1,1>": {
                    "<161,1,1,1>": "UI186 :The Popup displays sub-valued data from a specified column of a table row",
                    "<161,1,1,2>": "",
                    "<161,1,1,3>": "On the following page, specify the table name, row ID, and column (field position) to use.  In the column layout, the 'Column ID' specifies the value position in the specified column of the row."
                }
            }
        },
        "<162>": {
            "<162,1>": {
                "<162,1,1>": {
                    "<162,1,1,1>": "UI187 :",
                    "<162,1,1,2>": "",
                    "<162,1,1,3>": "On the following page, select a table to use as the data source then select the columns from the table to display in the Popup."
                }
            }
        },
        "<163>": "UI188 :The Popup selects rows from a table and displays specified columns.",
        "<164>": {
            "<164,1>": {
                "<164,1,1>": {
                    "<164,1,1,1>": "UI189 :",
                    "<164,1,1,2>": "",
                    "<164,1,1,3>": "Reduction and sorting criteria are specified in the 'Selection Criteria' box using the R/List syntax."
                }
            }
        },
        "<165>": {
            "<165,1>": {
                "<165,1,1>": {
                    "<165,1,1,1>": "UI190 :",
                    "<165,1,1,2>": "",
                    "<165,1,1,3>": "The list of keys is specified by entering them (one per line) in the 'List of Keys' box."
                }
            }
        },
        "<166>": {
            "<166,1>": {
                "<166,1,1>": {
                    "<166,1,1,1>": "UI191 :",
                    "<166,1,1,2>": "",
                    "<166,1,1,3>": "The cursor number, 0-8, is specified in the 'Cursor Number' box."
                }
            }
        },
        "<167>": "UI200 :Select Notes Documents",
        "<168>": "UI201 :Selection Formula",
        "<169>": "UI202 :Select DataSet Arguments and Columns",
        "<170>": "UI203 :Arguments",
        "<171>": "UI204 :Select Table Rows and Columns",
        "<172>": "UI205 :Selection Criteria",
        "<173>": "UI206 :Specify Table Rows and Select Table Columns",
        "<174>": "UI207 :List of Keys",
        "<175>": "UI208 :Specify Cursor and Select Table Columns",
        "<176>": "UI209 :Cursor Number",
        "<177>": "UI210 :Enter Literal Data to Display",
        "<178>": "UI211 :Literal Data",
        "<179>": "UI212 :Select Table and Row",
        "<180>": "UI213 :Row ID",
        "<181>": "UI214 :{Row}",
        "<182>": "UI215 :{Column}",
        "<183>": "UI216 :Select Table, Row and Column",
        "<184>": "UI217 :Row ID and Column",
        "<185>": "UI218 :Invalid Mode Selected",
        "<186>": "UI219 :Database",
        "<187>": "UI220 :DataSet",
        "<188>": "UI221 :Table",
        "<189>": "UI222 :Doc ID",
        "<190>": "UI223 :Document Field",
        "<191>": "UI224 :Row ID",
        "<192>": "UI225 :DataSet Column",
        "<193>": "UI226 :Table Column",
        "<194>": "UI227 :Component Field",
        "<195>": "UI228 :Table \"%1%\" is not attached.  Press <Alt-Down> for a list of available tables",
        "<196>": "UI229 :Database \"%1%\" has not been registered.  Press <Alt-Down> for a list of registered Notes databases",
        "<197>": "UI230 :Internal calculation error.  Contact Technical Support",
        "<198>": "UI231 :Are you sure you want to remove all selected items?",
        "<199>": "UI232 :Popup Designer",
        "<200>": "UI233 :%Default%",
        "<201>": "UI234 : <Truncated>",
        "<202>": "UI235 : <Empty>",
        "<203>": "UI236 : - <%1% Locked>",
        "<204>": "UI237 :&Stop",
        "<205>": "",
        "<206>": "UI250 :The Deployment Definition record: %1% is in use elsewhere and cannot be modified.",
        "<207>": "UI251 :Deployment Definition",
        "<208>": "UI252 :Save changes to Deployment Definition - %1%",
        "<209>": "UI253 :Repository View",
        "<210>": "UI254 :\"%1%\" already exists.||Replace existing item?",
        "<211>": "UI255 :The Repository View record: %1% is in use elsewhere and cannot be modified.",
        "<212>": "UI256 :Save changes to Repository View - %1%",
        "<213>": "UI257 :Extraction Path",
        "<214>": "UI258 :Deploy,Do Not Deploy,Deploy Empty",
        "<215>": "UI259 :\"%1%\" does not exist.",
        "<216>": "UI260 :Do you really want to delete item %1%",
        "<217>": "UI261 :Extraction progress,Repository Creation,Database Extraction,Entity Extraction,Prepare Application",
        "<218>": "UI262 :The specified directory does not exist. Create directory now?",
        "<219>": "UI263 :Initializing Repository Tables...",
        "<220>": "UI264 :Creating Repository Table: %1%",
        "<221>": "UI265 :Copying Repository Table: %1%",
        "<222>": "UI266 :Copying System Rows Into: %1%",
        "<223>": "UI267 :Build Target Repository Index...",
        "<224>": "UI268 :Continue current extraction from failure point?",
        "<225>": "UI269 :Extraction succeeded!",
        "<226>": "UI270 :Creating Database Table:  %1%",
        "<227>": "UI271 :Copying Database Table:  %1%",
        "<228>": "UI272 :Loading View:  %1%",
        "<229>": "UI273 :Extracting:  %1%",
        "<230>": "UI274 :Preparing Entity Storage...",
        "<231>": "UI275 :The specified directory contains data and cannot be written to.",
        "<232>": "UI276 :Delete files created by extraction process?",
        "<233>": "UI277 :Options",
        "<234>": "UI278 :<User Defined>",
        "<235>": "UI279 :<None>",
        "<236>": "UI280 :<All Publishable>",
        "<237>": "UI281 :Untitled",
        "<238>": "UI282 :Create Repository,Extract Database,Extract Entities,Prepare Application",
        "<239>": "UI283 :Full Deployment,Application Deployment,Application Upgrade",
        "<240>": "UI284 :Too many items to display in listbox. List truncated!",
        "<241>": "UI285 :No entity selected for alteration!",
        "<242>": "UI286 :Rebuilding the Repository Index.",
        "<243>": "UI287 :Building Database Definitions.",
        "<244>": "UI288 :Saving Application Definitions.",
        "<245>": "UI289 :Rebuilding Relational Indexes.",
        "<246>": "UI290 :Saving Deployment Definition.",
        "<247>": "UI291 :Table Processing",
        "<248>": "UI292 :Extract",
        "<249>": "UI293 :Item",
        "<250>": "UI294 :Item Type",
        "<251>": "UI295 :Connection,DataSet",
        "<252>": "UI296 :&Entity Name:",
        "<253>": "UI297 :Create Alias,Do Not Create",
        "<254>": "UI298 :Creating Alias: %1%",
        "<255>": "",
        "<256>": "UI400 :&Abort",
        "<257>": "UI401 :&Retry",
        "<258>": "UI402 :&Ignore",
        "<259>": "UI403 :The Message has been modified.  Do you want to save the changes?",
        "<260>": "UI404 :&Help",
        "<261>": "UI405 :Table %1% has changed.  Do you want to save changes?",
        "<262>": "UI406 :An error occured reading the Message.",
        "<263>": "UI407 :An error occured writing the Message.",
        "<264>": "UI408 :Unable to lock the \"%1%\" Message.",
        "<265>": "UI409 :Escape character was returned.",
        "<266>": "UI410 :Null was returned.",
        "<267>": "UI411 :Unable to save.  Duplicate name found:  \"%1%\".",
        "<268>": "UI412 :The Connection definition has been modified.  Do you want to save the changes?",
        "<269>": "UI413 :An error occured reading the Connection definition.",
        "<270>": "UI414 :An error occured writing the Connection definition.",
        "<271>": "UI415 :Unable to lock the \"%1%\" Connection definition.",
        "<272>": "UI416 :Select Objects Types",
        "<273>": "UI417 :Tables,Views,System Tables,Temporary Tables",
        "<274>": "UI418 :%1% Objects Processed; to view an object's columns,|select the object's row and choose \"Query-List Columns\"",
        "<275>": "UI419 :%1% Rows Processed",
        "<276>": "UI420 :The DataSet has been modified.  Do you want to save the changes?",
        "<277>": "UI421 :An error occured reading the DataSet definition.",
        "<278>": "UI422 :An error occured writing the DataSet definition.",
        "<279>": "UI423 :Unable to lock the \"%1%\" DataSet definition.",
        "<280>": "UI424 :No %1% Connection is defined for the \"%2%\" Data Source.",
        "<281>": "UI425 :Double click or use Alt-Down for options on Data Type, Nulls, or Key.",
        "<282>": "UI426 :Connecting to %1%...",
        "<283>": "UI427 :Closing Connection to %1%...",
        "<284>": "UI428 :Find",
        "<285>": "UI429 :Cannot find \"%1%\"",
        "<286>": "UI430 :Return value:  \"%1%\"",
        "<287>": "UI431 :The QuickHelp has been modified.  Do you want to save the changes?",
        "<288>": "UI432 :An error occured reading the QuickHelp definition.",
        "<289>": "UI433 :An error occured writing the QuickHelp definition.",
        "<290>": "UI434 :Unable to lock the \"%1%\" QuickHelp definition.",
        "<291>": {
            "<291,1>": "UI435 :,BO,A,,1,-1,-1,T,192",
            "<291,2>": "192",
            "<291,3>": "192,1",
            "<291,4>": "0",
            "<291,5>": {
                "<291,5,1>": "0,,Message,,,0,,1,Tahoma",
                "<291,5,2>": "-11",
                "<291,5,3>": "400",
                "<291,5,4>": "0",
                "<291,5,5>": "0",
                "<291,5,6>": "5",
                "<291,5,7>": "0",
                "<291,5,8>": "39",
                "<291,5,9>": "0",
                "<291,5,10>": "0",
                "<291,5,11>": "0",
                "<291,5,12>": "0",
                "<291,5,13>": "11",
                "<291,5,14>": "2",
                "<291,5,15>": "0",
                "<291,5,16>": "21,0"
            }
        },
        "<292>": {
            "<292,1>": {
                "<292,1,1>": "UI436 :-1,-1,-1,-1,16777215,Tahoma",
                "<292,1,2>": "-11",
                "<292,1,3>": "400",
                "<292,1,4>": "0",
                "<292,1,5>": "0",
                "<292,1,6>": "5",
                "<292,1,7>": "0",
                "<292,1,8>": "39",
                "<292,1,9>": "0",
                "<292,1,10>": "0",
                "<292,1,11>": "0",
                "<292,1,12>": "0",
                "<292,1,13>": "11",
                "<292,1,14>": "2",
                "<292,1,15>": "0",
                "<292,1,16>": "21,,,,L,1,,1,F,1,1,1,1,1,1,1,0,0,0,0,,,,0,0,0,0,0,,"
            }
        },
        "<293>": "",
        "<294>": "UI440 :Entity &Name",
        "<295>": "UI441 :List Entities of &Type",
        "<296>": "UI442 :Item &Name",
        "<297>": "UI443 :List Items of &Type",
        "<298>": "UI444 :\"%1%\" belongs to another application.||If you save it, a new item will be created in your application and the original will no longer be accessible.",
        "<299>": "UI445 :\"%1%\" belongs to another application.||Do you want to override it in the current application?",
        "<300>": ""
    }
}